[{"id":"002","startUp":"Eduardo's Brownies","nombre":"Brownie de Chocolate","precio":1,"stock":10,"imageURL":"public\/eesalava\/002.jpg","categoria":"cakes","descripcion":""},{"id":"003","startUp":"Andreas's Clothes","nombre":"Blusa blanca de rayas negras","precio":12,"stock":2,"imageURL":"public\/anvefran\/003.jpg","categoria":"clothes","descripcion":""},{"id":"001","startUp":"Eduardo's Brownies","nombre":"Brownie de Vainilla","precio":1.5,"stock":12,"imageURL":"public\/eesalava\/001.jpg","categoria":"cakes","descripcion":""},{"id":"004","startUp":"Alfajores de Gabriel","nombre":"Alfajor","precio":0.25,"stock":30,"imageURL":"public\/glorona\/004.jpg","categoria":"cakes","descripcion":""}]